askui_ml_helper-0.1.4.dist-info/METADATA
askui_ml_helper-0.1.4.dist-info/WHEEL
askui_ml_helper-0.1.4.dist-info/licenses/LICENSE
askui_ml_helper/__init__.py
askui_ml_helper/utils/image.py
askui_ml_helper/utils/pta_text.py
askui_ml_helper-0.1.4.dist-info/RECORD
